{
  "cross_sections": [
    {
      "candidate_sample_count": 324,
      "field_errors": [
        {
          "candidate_max": 1.563288688659667,
          "candidate_min": 0.0,
          "compared_count": 108,
          "field": "h",
          "l1": 3.349817081931681e-09,
          "l2": 1.056463282856554e-08,
          "linf": 5.3196452576287356e-08,
          "reference_max": 1.563288688659668,
          "reference_min": 0.0,
          "sample_count": 108
        },
        {
          "candidate_max": 2.8211546896160993,
          "candidate_min": -0.16365609372715695,
          "compared_count": 108,
          "field": "eta",
          "l1": 3.349817081514815e-09,
          "l2": 1.056463282856554e-08,
          "linf": 5.3196452576287356e-08,
          "reference_max": 2.8211546896160993,
          "reference_min": -0.1636560937271586,
          "sample_count": 108
        },
        {
          "candidate_max": 2.9164428392096475,
          "candidate_min": -0.9038338305736571,
          "compared_count": 45,
          "field": "u",
          "l1": 2.037428566168151e-08,
          "l2": 4.4408241887965494e-08,
          "linf": 1.447016133582224e-07,
          "reference_max": 2.9164428392096506,
          "reference_min": -0.9038338305736633,
          "sample_count": 108
        },
        {
          "candidate_max": 2.5965690300068753,
          "candidate_min": -1.1101321260954267,
          "compared_count": 45,
          "field": "v",
          "l1": 9.853443686191421e-15,
          "l2": 1.7363765169581456e-14,
          "linf": 8.403318027931932e-14,
          "reference_max": 2.596569030006881,
          "reference_min": -1.1101321260954382,
          "sample_count": 108
        },
        {
          "candidate_max": 1.4908029434521968,
          "candidate_min": 0.058899139308713135,
          "compared_count": 45,
          "field": "froude",
          "l1": 7.706753888299851e-09,
          "l2": 1.6828212108330867e-08,
          "linf": 5.8369906574817776e-08,
          "reference_max": 1.4908029434522019,
          "reference_min": 0.058899139308718436,
          "sample_count": 108
        }
      ],
      "kind": "cross_section",
      "max_distance_delta": 3.552713678800501e-15,
      "max_time_delta": 2.3092638912203256e-14,
      "reference_sample_count": 108,
      "sample_id": "mid_cross_section"
    }
  ],
  "point_probes": [
    {
      "candidate_sample_count": 9,
      "field_errors": [
        {
          "candidate_max": 1.1497704098814934,
          "candidate_min": 1.0277142524719238,
          "compared_count": 3,
          "field": "h",
          "l1": 1.0271675436139086e-08,
          "l2": 1.779106360605259e-08,
          "linf": 3.0815026086372654e-08,
          "reference_max": 1.1497703790664673,
          "reference_min": 1.0277142524719238,
          "sample_count": 3
        },
        {
          "candidate_max": 0.876,
          "candidate_min": 0.7539438425904305,
          "compared_count": 3,
          "field": "eta",
          "l1": 1.0271675436139086e-08,
          "l2": 1.779106360605259e-08,
          "linf": 3.0815026086372654e-08,
          "reference_max": 0.8759999691849739,
          "reference_min": 0.7539438425904305,
          "sample_count": 3
        },
        {
          "candidate_max": 1.5471311085429909,
          "candidate_min": 0.9234071507414622,
          "compared_count": 3,
          "field": "u",
          "l1": 7.971088752019758e-09,
          "l2": 1.3806329299966417e-08,
          "linf": 2.391326381356862e-08,
          "reference_max": 1.5471311324562547,
          "reference_min": 0.9234071507414606,
          "sample_count": 3
        },
        {
          "candidate_max": 1.883930913797322e-24,
          "candidate_min": -0.5614313128777637,
          "compared_count": 3,
          "field": "v",
          "l1": 7.586524001605236e-16,
          "l2": 1.0240766828629889e-15,
          "linf": 1.6653345369377348e-15,
          "reference_max": 1.883930945514759e-24,
          "reference_min": -0.5614313128777654,
          "sample_count": 3
        },
        {
          "candidate_max": 1.7788455688098839,
          "candidate_min": 0.9489986896514909,
          "compared_count": 3,
          "field": "hu",
          "l1": 6.726708634552381e-09,
          "l2": 1.1650999520288142e-08,
          "linf": 2.018012312809958e-08,
          "reference_max": 1.7788455486297607,
          "reference_min": 0.9489986896514893,
          "sample_count": 3
        },
        {
          "candidate_max": 2.1660880189451633e-24,
          "candidate_min": -0.5769909620285018,
          "compared_count": 3,
          "field": "hv",
          "l1": 7.586524001605236e-16,
          "l2": 1.0240766828629889e-15,
          "linf": 1.6653345369377348e-15,
          "reference_max": 2.1660879973595524e-24,
          "reference_min": -0.5769909620285034,
          "sample_count": 3
        },
        {
          "candidate_max": 1.0,
          "candidate_min": 1.0,
          "compared_count": 3,
          "field": "wet",
          "l1": 0.0,
          "l2": 0.0,
          "linf": 0.0,
          "reference_max": 1.0,
          "reference_min": 1.0,
          "sample_count": 3
        },
        {
          "candidate_max": 0.46066694550460613,
          "candidate_min": 0.3403529439149935,
          "compared_count": 3,
          "field": "froude",
          "l1": 4.431160623615445e-09,
          "l2": 7.674995144304274e-09,
          "linf": 1.3293481537779428e-08,
          "reference_max": 0.46066695879808767,
          "reference_min": 0.3403529439149934,
          "sample_count": 3
        }
      ],
      "kind": "point",
      "max_distance_delta": null,
      "max_time_delta": 2.3092638912203256e-14,
      "reference_sample_count": 3,
      "sample_id": "upstream_center"
    },
    {
      "candidate_sample_count": 9,
      "field_errors": [
        {
          "candidate_max": 1.42217195034027,
          "candidate_min": 1.2348734094810205,
          "compared_count": 3,
          "field": "h",
          "l1": 1.5195307234705524e-09,
          "l2": 2.631903903922891e-09,
          "linf": 4.5585912822332375e-09,
          "reference_max": 1.422171950340271,
          "reference_min": 1.2348734140396118,
          "sample_count": 3
        },
        {
          "candidate_max": 0.7392985408592496,
          "candidate_min": 0.552,
          "compared_count": 3,
          "field": "eta",
          "l1": 1.5195307234705524e-09,
          "l2": 2.631903903922891e-09,
          "linf": 4.5585912822332375e-09,
          "reference_max": 0.7392985408592505,
          "reference_min": 0.5520000045585913,
          "sample_count": 3
        },
        {
          "candidate_max": 2.1542514925844607,
          "candidate_min": 0.005687922185194458,
          "compared_count": 3,
          "field": "u",
          "l1": 3.2330973768572115e-08,
          "l2": 5.599888560376387e-08,
          "linf": 9.699291503295626e-08,
          "reference_max": 2.1542513955915457,
          "reference_min": 0.005687922185192459,
          "sample_count": 3
        },
        {
          "candidate_max": 0.8535993400014735,
          "candidate_min": -1.1101321260954267,
          "compared_count": 3,
          "field": "v",
          "l1": 1.5121048227062057e-14,
          "l2": 1.9576543729737883e-14,
          "linf": 3.181842378075926e-14,
          "reference_max": 0.8535993400014755,
          "reference_min": -1.1101321260954382,
          "sample_count": 3
        },
        {
          "candidate_max": 2.6602278855273505,
          "candidate_min": 0.008089203387501694,
          "compared_count": 3,
          "field": "hu",
          "l1": 3.6651209421589837e-08,
          "l2": 6.348175209767731e-08,
          "linf": 1.0995361998666908e-07,
          "reference_max": 2.6602277755737305,
          "reference_min": 0.008089203387498856,
          "sample_count": 3
        },
        {
          "candidate_max": 1.0868902206420874,
          "candidate_min": -1.5787987709045237,
          "compared_count": 3,
          "field": "hv",
          "l1": 2.1396135468630694e-14,
          "l2": 2.756591123046626e-14,
          "linf": 4.4426436567564296e-14,
          "reference_max": 1.0868902206420898,
          "reference_min": -1.578798770904541,
          "sample_count": 3
        },
        {
          "candidate_max": 1.0,
          "candidate_min": 1.0,
          "compared_count": 3,
          "field": "wet",
          "l1": 0.0,
          "l2": 0.0,
          "linf": 0.0,
          "reference_max": 1.0,
          "reference_min": 1.0,
          "sample_count": 3
        },
        {
          "candidate_max": 0.6189430337682208,
          "candidate_min": 0.26076111033685473,
          "compared_count": 3,
          "field": "froude",
          "l1": 9.669897475343229e-09,
          "l2": 1.6748751936511407e-08,
          "linf": 2.900968931740522e-08,
          "reference_max": 0.6189430047585315,
          "reference_min": 0.2607611103368548,
          "sample_count": 3
        }
      ],
      "kind": "point",
      "max_distance_delta": null,
      "max_time_delta": 2.3092638912203256e-14,
      "reference_sample_count": 3,
      "sample_id": "midstream_center"
    },
    {
      "candidate_sample_count": 9,
      "field_errors": [
        {
          "candidate_max": 1.354570150375365,
          "candidate_min": 1.1792105436325075,
          "compared_count": 3,
          "field": "h",
          "l1": 4.680860736054153e-09,
          "l2": 8.107487848814996e-09,
          "linf": 1.4042580875894828e-08,
          "reference_max": 1.3545701503753662,
          "reference_min": 1.1792105436325073,
          "sample_count": 3
        },
        {
          "candidate_max": 0.27915272018882,
          "candidate_min": 0.10379311344596243,
          "compared_count": 3,
          "field": "eta",
          "l1": 4.680860736054153e-09,
          "l2": 8.107487848814996e-09,
          "linf": 1.4042580875894828e-08,
          "reference_max": 0.2791527201888211,
          "reference_min": 0.1037931134459622,
          "sample_count": 3
        },
        {
          "candidate_max": 1.8636993543363378,
          "candidate_min": 1.6289966523233326,
          "compared_count": 3,
          "field": "u",
          "l1": 2.8963615950061694e-09,
          "l2": 5.016644542259377e-09,
          "linf": 8.689083230706274e-09,
          "reference_max": 1.8636993456472546,
          "reference_min": 1.6289966523233321,
          "sample_count": 3
        },
        {
          "candidate_max": 0.16285182070039875,
          "candidate_min": 0.09998144849254957,
          "compared_count": 3,
          "field": "v",
          "l1": 1.4092404095518891e-09,
          "l2": 2.440875717003341e-09,
          "linf": 4.227720756810882e-09,
          "reference_max": 0.16285182070039886,
          "reference_min": 0.09998144849254921,
          "sample_count": 3
        },
        {
          "candidate_max": 2.475483655929562,
          "candidate_min": 1.9209300279617318,
          "compared_count": 3,
          "field": "hu",
          "l1": 4.948550310264939e-09,
          "l2": 8.57113799723962e-09,
          "linf": 1.484564648990272e-08,
          "reference_max": 2.4754836559295654,
          "reference_min": 1.920930027961731,
          "sample_count": 3
        },
        {
          "candidate_max": 0.19203658401966087,
          "candidate_min": 0.1354318857192997,
          "compared_count": 3,
          "field": "hv",
          "l1": 1.3228374044308804e-09,
          "l2": 2.2912213222071213e-09,
          "linf": 3.9685117414478555e-09,
          "reference_max": 0.19203658401966095,
          "reference_min": 0.13543188571929932,
          "sample_count": 3
        },
        {
          "candidate_max": 1.0,
          "candidate_min": 1.0,
          "compared_count": 3,
          "field": "wet",
          "l1": 0.0,
          "l2": 0.0,
          "linf": 0.0,
          "reference_max": 1.0,
          "reference_min": 1.0,
          "sample_count": 3
        },
        {
          "candidate_max": 0.5220980779254121,
          "candidate_min": 0.48133720902945204,
          "compared_count": 3,
          "field": "froude",
          "l1": 1.7692464900539069e-09,
          "l2": 3.0644246836887617e-09,
          "linf": 5.307739248117116e-09,
          "reference_max": 0.5220980726176728,
          "reference_min": 0.48133720902945204,
          "sample_count": 3
        }
      ],
      "kind": "point",
      "max_distance_delta": null,
      "max_time_delta": 2.3092638912203256e-14,
      "reference_sample_count": 3,
      "sample_id": "downstream_center"
    },
    {
      "candidate_sample_count": 9,
      "field_errors": [
        {
          "candidate_max": 1.509736168076775,
          "candidate_min": 1.052717447280885,
          "compared_count": 3,
          "field": "h",
          "l1": 4.076236089408288e-09,
          "l2": 7.060246728525961e-09,
          "linf": 1.2228706047778815e-08,
          "reference_max": 1.509736180305481,
          "reference_min": 1.0527174472808838,
          "sample_count": 3
        },
        {
          "candidate_max": 1.092,
          "candidate_min": 0.6349812792041101,
          "compared_count": 3,
          "field": "eta",
          "l1": 4.076236089408288e-09,
          "l2": 7.060246728525961e-09,
          "linf": 1.2228706047778815e-08,
          "reference_max": 1.0920000122287061,
          "reference_min": 0.634981279204109,
          "sample_count": 3
        },
        {
          "candidate_max": 2.792880320986645,
          "candidate_min": 0.9815470430086262,
          "compared_count": 3,
          "field": "u",
          "l1": 5.842967409908084e-08,
          "l2": 1.0120316094026275e-07,
          "linf": 1.752890166351051e-07,
          "reference_max": 2.7928801456976284,
          "reference_min": 0.9815470430086218,
          "sample_count": 3
        },
        {
          "candidate_max": 0.28820579120839485,
          "candidate_min": -0.27472627509339526,
          "compared_count": 3,
          "field": "v",
          "l1": 1.313763912473102e-15,
          "l2": 1.929628088298016e-15,
          "linf": 3.2751579226442118e-15,
          "reference_max": 0.2882057912083955,
          "reference_min": -0.27472627509339853,
          "sample_count": 3
        },
        {
          "candidate_max": 4.216512433703411,
          "candidate_min": 1.0332916975021418,
          "compared_count": 3,
          "field": "hu",
          "l1": 7.682895556785733e-08,
          "l2": 1.3307164953627775e-07,
          "linf": 2.304868580438324e-07,
          "reference_max": 4.216512203216553,
          "reference_min": 1.0332916975021362,
          "sample_count": 3
        },
        {
          "candidate_max": 0.30339926481246915,
          "candidate_min": -0.33961045742034474,
          "compared_count": 3,
          "field": "hv",
          "l1": 1.572815951552305e-15,
          "l2": 2.5391927600105436e-15,
          "linf": 4.385380947269368e-15,
          "reference_max": 0.3033992648124695,
          "reference_min": -0.3396104574203491,
          "sample_count": 3
        },
        {
          "candidate_max": 1.0,
          "candidate_min": 1.0,
          "compared_count": 3,
          "field": "wet",
          "l1": 0.0,
          "l2": 0.0,
          "linf": 0.0,
          "reference_max": 1.0,
          "reference_min": 1.0,
          "sample_count": 3
        },
        {
          "candidate_max": 0.7257169932692831,
          "candidate_min": 0.3183307674024147,
          "compared_count": 3,
          "field": "froude",
          "l1": 1.6162385059933133e-08,
          "l2": 2.7994071197913763e-08,
          "linf": 4.848715362548717e-08,
          "reference_max": 0.7257169447821294,
          "reference_min": 0.3183307674024136,
          "sample_count": 3
        }
      ],
      "kind": "point",
      "max_distance_delta": null,
      "max_time_delta": 2.3092638912203256e-14,
      "reference_sample_count": 3,
      "sample_id": "feature_0_constriction"
    },
    {
      "candidate_sample_count": 9,
      "field_errors": [
        {
          "candidate_max": 0.8850898242891944,
          "candidate_min": 0.4501459002494822,
          "compared_count": 3,
          "field": "h",
          "l1": 3.208754521348093e-09,
          "l2": 5.557724385719961e-09,
          "linf": 9.626261010531323e-09,
          "reference_max": 0.8850898146629333,
          "reference_min": 0.4501459002494812,
          "sample_count": 3
        },
        {
          "candidate_max": 0.948,
          "candidate_min": 0.5130560759602878,
          "compared_count": 3,
          "field": "eta",
          "l1": 3.208754521348093e-09,
          "l2": 5.557724385719961e-09,
          "linf": 9.626261010531323e-09,
          "reference_max": 0.9479999903737389,
          "reference_min": 0.5130560759602868,
          "sample_count": 3
        },
        {
          "candidate_max": 2.2265518474740573,
          "candidate_min": 0.7593079196802344,
          "compared_count": 3,
          "field": "u",
          "l1": 2.029855394880542e-09,
          "l2": 3.5158088300269426e-09,
          "linf": 6.089559523303478e-09,
          "reference_max": 2.226551841384498,
          "reference_min": 0.759307919680229,
          "sample_count": 3
        },
        {
          "candidate_max": 0.06379588152848263,
          "candidate_min": -0.8877564339983823,
          "compared_count": 3,
          "field": "v",
          "l1": 1.864249495516409e-15,
          "l2": 3.1420754101792395e-15,
          "linf": 5.440092820663267e-15,
          "reference_max": 0.06379588152848278,
          "reference_min": -0.8877564339983878,
          "sample_count": 3
        },
        {
          "candidate_max": 1.9706983834515945,
          "candidate_min": 0.550248026847842,
          "compared_count": 3,
          "field": "hu",
          "l1": 8.94106052159079e-09,
          "l2": 1.548636821249964e-08,
          "linf": 2.682317656876876e-08,
          "reference_max": 1.970698356628418,
          "reference_min": 0.5502480268478394,
          "sample_count": 3
        },
        {
          "candidate_max": 0.028717454522848126,
          "candidate_min": -0.6433308720588631,
          "compared_count": 3,
          "field": "hv",
          "l1": 1.7775133217175685e-15,
          "l2": 3.0767409502599e-15,
          "linf": 5.329070518200751e-15,
          "reference_max": 0.02871745452284813,
          "reference_min": -0.6433308720588684,
          "sample_count": 3
        },
        {
          "candidate_max": 1.0,
          "candidate_min": 1.0,
          "compared_count": 3,
          "field": "wet",
          "l1": 0.0,
          "l2": 0.0,
          "linf": 0.0,
          "reference_max": 1.0,
          "reference_min": 1.0,
          "sample_count": 3
        },
        {
          "candidate_max": 0.7968618734847752,
          "candidate_min": 0.43813449345837235,
          "compared_count": 3,
          "field": "froude",
          "l1": 6.808258216454514e-10,
          "l2": 1.1792246257503635e-09,
          "linf": 2.042476965335993e-09,
          "reference_max": 0.7968618734847754,
          "reference_min": 0.4381344934583721,
          "sample_count": 3
        }
      ],
      "kind": "point",
      "max_distance_delta": null,
      "max_time_delta": 2.3092638912203256e-14,
      "reference_sample_count": 3,
      "sample_id": "feature_1_ledge"
    },
    {
      "candidate_sample_count": 9,
      "field_errors": [
        {
          "candidate_max": 1.3331948518753045,
          "candidate_min": 1.0644476525400934,
          "compared_count": 3,
          "field": "h",
          "l1": 3.7224716642469957e-09,
          "l2": 6.447508770236221e-09,
          "linf": 1.1167412772294938e-08,
          "reference_max": 1.3331948518753052,
          "reference_min": 1.0644476413726807,
          "sample_count": 3
        },
        {
          "candidate_max": 1.0907471993352111,
          "candidate_min": 0.8220000000000001,
          "compared_count": 3,
          "field": "eta",
          "l1": 3.7224716642469957e-09,
          "l2": 6.447508770236221e-09,
          "linf": 1.1167412772294938e-08,
          "reference_max": 1.0907471993352118,
          "reference_min": 0.8219999888325873,
          "sample_count": 3
        },
        {
          "candidate_max": 0.9362393641523836,
          "candidate_min": 0.522308270322127,
          "compared_count": 3,
          "field": "u",
          "l1": 5.131913708803874e-09,
          "l2": 8.8887340017325e-09,
          "linf": 1.5395738905965572e-08,
          "reference_max": 0.9362393795481225,
          "reference_min": 0.5223082703221249,
          "sample_count": 3
        },
        {
          "candidate_max": 8.615271208561372e-21,
          "candidate_min": -0.2796645194185514,
          "compared_count": 3,
          "field": "v",
          "l1": 2.4054832200225243e-16,
          "l2": 3.5832294041243816e-16,
          "linf": 6.106226635438361e-16,
          "reference_max": 8.615271614017996e-21,
          "reference_min": -0.2796645194185515,
          "sample_count": 3
        },
        {
          "candidate_max": 1.1879529953002925,
          "candidate_min": 0.5624666810035737,
          "compared_count": 3,
          "field": "hu",
          "l1": 1.977530028618446e-09,
          "l2": 3.4251804319005653e-09,
          "linf": 5.932586533141659e-09,
          "reference_max": 1.187952995300293,
          "reference_min": 0.5624666810035706,
          "sample_count": 3
        },
        {
          "candidate_max": 9.170505213949406e-21,
          "candidate_min": -0.34855926036834617,
          "compared_count": 3,
          "field": "hv",
          "l1": 4.255854927730885e-16,
          "l2": 5.987317933058821e-16,
          "linf": 9.992007221626409e-16,
          "reference_max": 9.170505549326463e-21,
          "reference_min": -0.34855926036834717,
          "sample_count": 3
        },
        {
          "candidate_max": 1.0,
          "candidate_min": 1.0,
          "compared_count": 3,
          "field": "wet",
          "l1": 0.0,
          "l2": 0.0,
          "linf": 0.0,
          "reference_max": 1.0,
          "reference_min": 1.0,
          "sample_count": 3
        },
        {
          "candidate_max": 0.28972784698269743,
          "candidate_min": 0.18228265583132253,
          "compared_count": 3,
          "field": "froude",
          "l1": 2.094720054820106e-09,
          "l2": 3.628161290162181e-09,
          "linf": 6.284159692615532e-09,
          "reference_max": 0.2897278532668571,
          "reference_min": 0.1822826558313221,
          "sample_count": 3
        }
      ],
      "kind": "point",
      "max_distance_delta": null,
      "max_time_delta": 2.3092638912203256e-14,
      "reference_sample_count": 3,
      "sample_id": "feature_2_hole"
    },
    {
      "candidate_sample_count": 9,
      "field_errors": [
        {
          "candidate_max": 0.0,
          "candidate_min": 0.0,
          "compared_count": 3,
          "field": "h",
          "l1": 0.0,
          "l2": 0.0,
          "linf": 0.0,
          "reference_max": 0.0,
          "reference_min": 0.0,
          "sample_count": 3
        },
        {
          "candidate_max": 2.682,
          "candidate_min": 2.682,
          "compared_count": 3,
          "field": "eta",
          "l1": 0.0,
          "l2": 0.0,
          "linf": 0.0,
          "reference_max": 2.682,
          "reference_min": 2.682,
          "sample_count": 3
        },
        {
          "candidate_max": 0.0,
          "candidate_min": 0.0,
          "compared_count": 0,
          "field": "u",
          "l1": 0.0,
          "l2": 0.0,
          "linf": 0.0,
          "reference_max": 0.0,
          "reference_min": 0.0,
          "sample_count": 3
        },
        {
          "candidate_max": 0.0,
          "candidate_min": 0.0,
          "compared_count": 0,
          "field": "v",
          "l1": 0.0,
          "l2": 0.0,
          "linf": 0.0,
          "reference_max": 0.0,
          "reference_min": 0.0,
          "sample_count": 3
        },
        {
          "candidate_max": 0.0,
          "candidate_min": 0.0,
          "compared_count": 3,
          "field": "hu",
          "l1": 0.0,
          "l2": 0.0,
          "linf": 0.0,
          "reference_max": 0.0,
          "reference_min": 0.0,
          "sample_count": 3
        },
        {
          "candidate_max": 0.0,
          "candidate_min": 0.0,
          "compared_count": 3,
          "field": "hv",
          "l1": 0.0,
          "l2": 0.0,
          "linf": 0.0,
          "reference_max": 0.0,
          "reference_min": 0.0,
          "sample_count": 3
        },
        {
          "candidate_max": 0.0,
          "candidate_min": 0.0,
          "compared_count": 3,
          "field": "wet",
          "l1": 0.0,
          "l2": 0.0,
          "linf": 0.0,
          "reference_max": 0.0,
          "reference_min": 0.0,
          "sample_count": 3
        },
        {
          "candidate_max": 0.0,
          "candidate_min": 0.0,
          "compared_count": 0,
          "field": "froude",
          "l1": 0.0,
          "l2": 0.0,
          "linf": 0.0,
          "reference_max": 0.0,
          "reference_min": 0.0,
          "sample_count": 3
        }
      ],
      "kind": "point",
      "max_distance_delta": null,
      "max_time_delta": 2.3092638912203256e-14,
      "reference_sample_count": 3,
      "sample_id": "feature_3_strainer"
    },
    {
      "candidate_sample_count": 9,
      "field_errors": [
        {
          "candidate_max": 0.0027379048988223037,
          "candidate_min": 0.0,
          "compared_count": 3,
          "field": "h",
          "l1": 2.8912057932946786e-18,
          "l2": 3.5586503723825945e-18,
          "linf": 4.7704895589362195e-18,
          "reference_max": 0.0027379048988223076,
          "reference_min": 0.0,
          "sample_count": 3
        },
        {
          "candidate_max": 2.5587379048988224,
          "candidate_min": 2.556,
          "compared_count": 3,
          "field": "eta",
          "l1": 0.0,
          "l2": 0.0,
          "linf": 0.0,
          "reference_max": 2.5587379048988224,
          "reference_min": 2.556,
          "sample_count": 3
        },
        {
          "candidate_max": 0.051270362546401854,
          "candidate_min": 0.0,
          "compared_count": 0,
          "field": "u",
          "l1": 0.0,
          "l2": 0.0,
          "linf": 0.0,
          "reference_max": 0.05127036254640192,
          "reference_min": 0.0,
          "sample_count": 3
        },
        {
          "candidate_max": 0.0,
          "candidate_min": -0.0069340179984335015,
          "compared_count": 0,
          "field": "v",
          "l1": 0.0,
          "l2": 0.0,
          "linf": 0.0,
          "reference_max": 0.0,
          "reference_min": -0.006934017998433518,
          "sample_count": 3
        },
        {
          "candidate_max": 0.0001403733767801892,
          "candidate_min": 0.0,
          "compared_count": 3,
          "field": "hu",
          "l1": 2.484629978612614e-19,
          "l2": 3.043540763508195e-19,
          "linf": 3.7947076036992655e-19,
          "reference_max": 0.00014037337678018957,
          "reference_min": 0.0,
          "sample_count": 3
        },
        {
          "candidate_max": 0.0,
          "candidate_min": -1.4652319805463781e-05,
          "compared_count": 3,
          "field": "hv",
          "l1": 2.371692252312041e-20,
          "l2": 3.8257394318196643e-20,
          "linf": 6.606856988583543e-20,
          "reference_max": 0.0,
          "reference_min": -1.4652319805463776e-05,
          "sample_count": 3
        },
        {
          "candidate_max": 1.0,
          "candidate_min": 0.0,
          "compared_count": 3,
          "field": "wet",
          "l1": 0.0,
          "l2": 0.0,
          "linf": 0.0,
          "reference_max": 1.0,
          "reference_min": 0.0,
          "sample_count": 3
        },
        {
          "candidate_max": 0.31453995193309986,
          "candidate_min": 0.0,
          "compared_count": 0,
          "field": "froude",
          "l1": 0.0,
          "l2": 0.0,
          "linf": 0.0,
          "reference_max": 0.3145399519331,
          "reference_min": 0.0,
          "sample_count": 3
        }
      ],
      "kind": "point",
      "max_distance_delta": null,
      "max_time_delta": 2.3092638912203256e-14,
      "reference_sample_count": 3,
      "sample_id": "feature_4_rock"
    },
    {
      "candidate_sample_count": 9,
      "field_errors": [
        {
          "candidate_max": 0.7621670961379988,
          "candidate_min": 0.43037563762447795,
          "compared_count": 3,
          "field": "h",
          "l1": 6.668492794995965e-10,
          "l2": 1.1550158075043026e-09,
          "linf": 2.00054606214195e-09,
          "reference_max": 0.7621670961380005,
          "reference_min": 0.4303756356239319,
          "sample_count": 3
        },
        {
          "candidate_max": 0.7577914585135209,
          "candidate_min": 0.42600000000000005,
          "compared_count": 3,
          "field": "eta",
          "l1": 6.668492794995965e-10,
          "l2": 1.1550158075043026e-09,
          "linf": 2.00054606214195e-09,
          "reference_max": 0.7577914585135226,
          "reference_min": 0.425999997999454,
          "sample_count": 3
        },
        {
          "candidate_max": 1.9538690477085607,
          "candidate_min": 1.7604520343044565,
          "compared_count": 3,
          "field": "u",
          "l1": 1.0540578780175261e-08,
          "l2": 1.82568176038534e-08,
          "linf": 3.162173567439197e-08,
          "reference_max": 1.953869016086825,
          "reference_min": 1.760452034304456,
          "sample_count": 3
        },
        {
          "candidate_max": 0.6802864962827208,
          "candidate_min": 0.0013995498547483838,
          "compared_count": 3,
          "field": "v",
          "l1": 1.4186618459838263e-11,
          "l2": 2.4570854296646307e-11,
          "linf": 4.2557968000372925e-11,
          "reference_max": 0.6802864962827212,
          "reference_min": 0.0013995498973063518,
          "sample_count": 3
        },
        {
          "candidate_max": 1.3650258779525724,
          "candidate_min": 0.8408976372423034,
          "compared_count": 3,
          "field": "hu",
          "l1": 5.839344341396213e-09,
          "l2": 1.011403915922556e-08,
          "linf": 1.7518029693519566e-08,
          "reference_max": 1.3650258779525757,
          "reference_min": 0.8408976197242737,
          "sample_count": 3
        },
        {
          "candidate_max": 0.5184919834136948,
          "candidate_min": 0.0006023321611245811,
          "compared_count": 3,
          "field": "hv",
          "l1": 5.172737852926952e-12,
          "l2": 8.958194898202684e-12,
          "linf": 1.551604862388284e-11,
          "reference_max": 0.5184919834136963,
          "reference_min": 0.0006023321766406298,
          "sample_count": 3
        },
        {
          "candidate_max": 1.0,
          "candidate_min": 1.0,
          "compared_count": 3,
          "field": "wet",
          "l1": 0.0,
          "l2": 0.0,
          "linf": 0.0,
          "reference_max": 1.0,
          "reference_min": 1.0,
          "sample_count": 3
        },
        {
          "candidate_max": 0.9509051975370232,
          "candidate_min": 0.7006433443663564,
          "compared_count": 3,
          "field": "froude",
          "l1": 4.3931674594451424e-09,
          "l2": 7.609188861324745e-09,
          "linf": 1.3179501712201613e-08,
          "reference_max": 0.9509051843575215,
          "reference_min": 0.7006433443663558,
          "sample_count": 3
        }
      ],
      "kind": "point",
      "max_distance_delta": null,
      "max_time_delta": 2.3092638912203256e-14,
      "reference_sample_count": 3,
      "sample_id": "feature_5_shallow"
    }
  ],
  "scenario_id": "eddy_line_shear_seed_20"
}